cosmocalc/__init__.py
cosmocalc/calculations.py
cosmocalc/utils.py
cosmocalc_dilru1-0.1.0.dist-info/METADATA
cosmocalc_dilru1-0.1.0.dist-info/WHEEL
cosmocalc_dilru1-0.1.0.dist-info/top_level.txt
cosmocalc_dilru1-0.1.0.dist-info/RECORD
